__init__.py
nyt_leaderboard_scraper/score.py
nyt_leaderboard_scraper/scraper.py
nyt_leaderboard_scraper-0.0.2.dist-info/licenses/LICENSE.md
nyt_leaderboard_scraper-0.0.2.dist-info/METADATA
nyt_leaderboard_scraper-0.0.2.dist-info/WHEEL
nyt_leaderboard_scraper-0.0.2.dist-info/top_level.txt
nyt_leaderboard_scraper-0.0.2.dist-info/RECORD
