Metadata-Version: 2.4
Name: nyt-leaderboard-scraper
Version: 0.0.2
Summary: A package to scrape the current NYT Mini Leaderboard.
Author-email: Rampiggy <rampiggy.support@proton.me>
License-Expression: MIT
Project-URL: Homepage, https://github.com/Rampiggy/nyt-leaderboard-scraper
Project-URL: Issues, https://github.com/Rampiggy/nyt-leaderboard-scraper/issues
Keywords: nyt,leaderboard,scraper,nyt leaderboard,nyt scraper,leaderboard scraper,nyt leaderboard scraper,nyt-leaderboard,nyt-scraper,leaderboard-scraper,nyt-leaderboard-scraper
Classifier: Programming Language :: Python :: 3
Classifier: Operating System :: OS Independent
Requires-Python: >=3.9
License-File: LICENSE.md
Dynamic: license-file
